setup.py
nilas/__init__.py
nilas.egg-info/PKG-INFO
nilas.egg-info/SOURCES.txt
nilas.egg-info/dependency_links.txt
nilas.egg-info/requires.txt
nilas.egg-info/top_level.txt