Metadata-Version: 1.0
Name: nilas
Version: 0.1.4
Summary: Python bindings for Nilas.
Home-page: UNKNOWN
Author: Nilas Team
Author-email: support@nilas.com
License: MIT
Keywords: nilas app appserver email
Platform: UNKNOWN
